codelink/__init__.py
codelink/app.py
codelink/app_fc.py
codelink/app_stats
codelink/app_style.py
codelink/cutter_item.py
codelink/dag_scene.py
codelink/edge_item.py
codelink/editor_widget.py
codelink/filter_model_test.py
codelink/frame_item.py
codelink/input_widgets.py
codelink/item_delegates.py
codelink/nested_data.py
codelink/node_item.py
codelink/node_list_action.py
codelink/node_reg.py
codelink/path_loader.py
codelink/pin_item.py
codelink/profiler.py
codelink/property_model.py
codelink/property_table.py
codelink/property_widget.py
codelink/socket_widget.py
codelink/test.py
codelink/undo_commands.py
codelink/utils.py
codelink/images_dark-light/Hmovetoolbar_dark.svg
codelink/images_dark-light/Hmovetoolbar_light.svg
codelink/images_dark-light/Hsepartoolbar_dark.svg
codelink/images_dark-light/Hsepartoolbar_light.svg
codelink/images_dark-light/Vmovetoolbar_dark.svg
codelink/images_dark-light/Vmovetoolbar_light.svg
codelink/images_dark-light/Vsepartoolbar_dark.svg
codelink/images_dark-light/Vsepartoolbar_light.svg
codelink/images_dark-light/background_freecad.svg
codelink/images_dark-light/background_freecad_dark.svg
codelink/images_dark-light/background_freecad_light.svg
codelink/images_dark-light/branch_end_closed_dark.svg
codelink/images_dark-light/branch_end_closed_light.svg
codelink/images_dark-light/branch_end_dark.svg
codelink/images_dark-light/branch_end_light.svg
codelink/images_dark-light/branch_end_open_dark.svg
codelink/images_dark-light/branch_end_open_light.svg
codelink/images_dark-light/branch_more_closed_dark.svg
codelink/images_dark-light/branch_more_closed_light.svg
codelink/images_dark-light/branch_more_dark.svg
codelink/images_dark-light/branch_more_light.svg
codelink/images_dark-light/branch_more_open_dark.svg
codelink/images_dark-light/branch_more_open_light.svg
codelink/images_dark-light/branch_vline_dark.svg
codelink/images_dark-light/branch_vline_light.svg
codelink/images_dark-light/checkbox_indeterminate_light.svg
codelink-0.0.26.dist-info/METADATA
codelink-0.0.26.dist-info/WHEEL
codelink-0.0.26.dist-info/licenses/LICENSE
codelink-0.0.26.dist-info/RECORD
