Metadata-Version: 2.1
Name: codelink
Version: 0.0.26
Summary: Node-based visual programming environment
Project-URL: Homepage, https://github.com/j8sr0230/codelink
Project-URL: Bug Tracker, https://github.com/j8sr0230/codelink/issues
Author-email: Ronny Scharf-Wildenhain <ronny.scharf08@gmail.com>
License-File: LICENSE
Classifier: License :: OSI Approved :: GNU Lesser General Public License v2 or later (LGPLv2+)
Classifier: Operating System :: OS Independent
Classifier: Programming Language :: Python :: 3
Requires-Python: >=3.10
Requires-Dist: awkward>=2.3.1
Requires-Dist: dask>=2023.2.1
Requires-Dist: ikpy>=3.3.4
Requires-Dist: matplotlib>=3.7.2
Requires-Dist: networkx>=3.1
Requires-Dist: numpy>=1.24.3
Requires-Dist: pyside2>=5.15.8
Requires-Dist: scipy>=1.11.1
